nexaas_id_client/__init__.py
nexaas_id_client/api_client.py
nexaas_id_client/exceptions.py
nexaas_id_client/oauth_client.py
nexaas_id_client/oauth_token.py
nexaas_id_client/support/__init__.py
nexaas_id_client/support/flask.py
nexaas_id_client/support/django/__init__.py
nexaas_id_client/support/django/decorators.py
nexaas_id_client/support/django/helpers.py
nexaas_id_client/support/django/model.py
nexaas_id_client/support/django/urls.py
nexaas_id_client/support/django/views.py
nexaas_id_client-1.0.1.dist-info/METADATA
nexaas_id_client-1.0.1.dist-info/RECORD
nexaas_id_client-1.0.1.dist-info/WHEEL
nexaas_id_client-1.0.1.dist-info/top_level.txt
